__init__.py
data_handling/__init__.py
data_handling/file_handler.py
data_processing/__init__.py
data_processing/data_processor.py
websites/__init__.py
websites/base.py
websites/douban.py
websites/imdb.py
websites/rottentomatoes.py
film_review_scraper-1.0.dist-info/LICENSE
film_review_scraper-1.0.dist-info/METADATA
film_review_scraper-1.0.dist-info/WHEEL
film_review_scraper-1.0.dist-info/top_level.txt
film_review_scraper-1.0.dist-info/RECORD
